kotnet/__init__.py
kotnet/kotnet.py
kotnet-0.1.2.dist-info/METADATA
kotnet-0.1.2.dist-info/WHEEL
kotnet-0.1.2.dist-info/top_level.txt
kotnet-0.1.2.dist-info/RECORD
